cythonpackage/__init__.py
cythonpackage/build.py
cythonpackage/init.py
cythonpackage/py.typed
cythonpackage-0.2.14.dist-info/AUTHORS
cythonpackage-0.2.14.dist-info/METADATA
cythonpackage-0.2.14.dist-info/WHEEL
cythonpackage-0.2.14.dist-info/entry_points.txt
cythonpackage-0.2.14.dist-info/top_level.txt
cythonpackage-0.2.14.dist-info/zip-safe
cythonpackage-0.2.14.dist-info/RECORD
