Metadata-Version: 2.1
Name: cythonpackage
Version: 0.2.14
Summary: Compile a package in one .so file and remove source code
Home-page: https://github.com/pprados/cythonpackage
Author: Philippe PRADOS
Author-email: cythonpackage@prados.fr
License: Apache-2.0
Project-URL: Bug Tracker, https://github.com/pprados/cythonpackage/issues
Project-URL: Documentation, https://github.com/pprados/cythonpackage/
Project-URL: Source Code, https://github.com/pprados/cythonpackage/
Keywords: cython
Platform: UNKNOWN
Classifier: Development Status :: 4 - Beta
Classifier: Intended Audience :: Developers
Classifier: License :: OSI Approved :: Apache Software License
Classifier: Programming Language :: Python
Classifier: Programming Language :: Python :: 3.7
Classifier: Programming Language :: Python :: 3.8
Classifier: Programming Language :: Python :: 3.9
Classifier: Programming Language :: Python :: 3.10
Classifier: Topic :: Software Development :: Libraries :: Python Modules
Requires-Python: >=3.6
Provides-Extra: build
Requires-Dist: setuptools (>=42) ; extra == 'build'
Requires-Dist: cython ; extra == 'build'
Provides-Extra: dev
Requires-Dist: cibuildwheel ; extra == 'dev'
Requires-Dist: twine ; extra == 'dev'
Requires-Dist: gitflow ; extra == 'dev'
Requires-Dist: pypiserver ; extra == 'dev'
Provides-Extra: poetry
Requires-Dist: poetry-core (>=1.0.0) ; extra == 'poetry'
Requires-Dist: setuptools (>=42) ; extra == 'poetry'
Requires-Dist: cython ; extra == 'poetry'
